appyratus/__init__.py
appyratus/constants.py
appyratus/enum.py
appyratus/env.py
appyratus/exc.py
appyratus/json.py
appyratus/logging.py
appyratus/memoize.py
appyratus/usage.py
appyratus/asynchronous/__init__.py
appyratus/asynchronous/http.py
appyratus/cli/__init__.py
appyratus/cli/arg.py
appyratus/cli/cli_program.py
appyratus/cli/parser.py
appyratus/cli/subparser.py
appyratus/files/__init__.py
appyratus/files/base.py
appyratus/files/css.py
appyratus/files/csv.py
appyratus/files/file.py
appyratus/files/html.py
appyratus/files/ini.py
appyratus/files/json.py
appyratus/files/shell.py
appyratus/files/text.py
appyratus/files/xml.py
appyratus/files/yaml.py
appyratus/files/markdown/__init__.py
appyratus/files/markdown/markdown_file.py
appyratus/files/markdown/markdown_utils.py
appyratus/files/python/__init__.py
appyratus/files/python/python_file.py
appyratus/files/python/python_utils.py
appyratus/reflection/__init__.py
appyratus/reflection/ast_parser.py
appyratus/reflection/python_ast.py
appyratus/schema/__init__.py
appyratus/schema/example.py
appyratus/schema/exc.py
appyratus/schema/fields.py
appyratus/schema/schema.py
appyratus/schema/fields/__init__.py
appyratus/schema/fields/field_adapter.py
appyratus/schema/fields/fields.py
appyratus/schema/fields/value_generator.py
appyratus/test/__init__.py
appyratus/test/base_tests.py
appyratus/test/file_type_tests.py
appyratus/test/mark.py
appyratus/utils/__init__.py
appyratus/utils/color_utils.py
appyratus/utils/dict_utils.py
appyratus/utils/func_utils.py
appyratus/utils/list_utils.py
appyratus/utils/path_utils.py
appyratus/utils/string_utils.py
appyratus/utils/sys_utils.py
appyratus/utils/template_utils.py
appyratus/utils/time_utils.py
appyratus/utils/type_utils.py
appyratus/utils/url_utils.py
appyratus-3.0.4.dist-info/LICENSE
appyratus-3.0.4.dist-info/METADATA
appyratus-3.0.4.dist-info/WHEEL
appyratus-3.0.4.dist-info/top_level.txt
appyratus-3.0.4.dist-info/RECORD
