Metadata-Version: 2.1
Name: appyratus
Version: 3.0.4
Summary: Not your momma's Python toolkit
Home-page: https://github.com/gigaquads/appyratus.git
Author: Gigaquads
Author-email: what@gigaquads.com
License: UNKNOWN
Platform: UNKNOWN
Classifier: Programming Language :: Python :: 3.9
Classifier: License :: OSI Approved :: MIT License
License-File: LICENSE
Requires-Dist: ipython (==7.19.0)
Requires-Dist: pytest (==6.1.2)
Requires-Dist: python-dateutil (==2.8.1)
Requires-Dist: pyyaml (==5.4.1)
Requires-Dist: pytz (==2020.4)
Requires-Dist: uvloop (==0.14.0)
Requires-Dist: jinja2 (==2.11.1)
Requires-Dist: python-rapidjson (==0.9.4)
Requires-Dist: aiohttp (>=3.7.4)
Requires-Dist: bcrypt (==3.2.0)
Requires-Dist: inflect (==5.0.2)
Requires-Dist: beautifulsoup4 (==4.9.3)
Requires-Dist: astor (==0.8.1)
Requires-Dist: webcolors (==1.11.1)
Requires-Dist: colormath (==3.0.0)
Requires-Dist: yapf (==0.30.0)
Requires-Dist: faker (==5.0.1)
Requires-Dist: jsbeautifier (==1.13.0)
Requires-Dist: mistune (==2.0.0rc1)
Requires-Dist: MarkupSafe (==2.0.1)
